yolo9/__init__.py
yolo9/benchmarks.py
yolo9/detect.py
yolo9/detect_dual.py
yolo9/export.py
yolo9/hubconf.py
yolo9/train.py
yolo9/train_dual.py
yolo9/train_triple.py
yolo9/val.py
yolo9/val_dual.py
yolo9/val_triple.py
yolo9/classify/predict.py
yolo9/classify/train.py
yolo9/classify/val.py
yolo9/data/__ini__.py
yolo9/data/class_names.py
yolo9/data/coco.yaml
yolo9/models/__init__.py
yolo9/models/common.py
yolo9/models/experimental.py
yolo9/models/tf.py
yolo9/models/yolo.py
yolo9/models/detect/gelan-c.yaml
yolo9/models/detect/gelan-e.yaml
yolo9/models/detect/gelan-m.yaml
yolo9/models/detect/gelan-s.yaml
yolo9/models/detect/gelan-t.yaml
yolo9/models/detect/gelan.yaml
yolo9/models/detect/yolov7-af.yaml
yolo9/models/detect/yolov9-c.yaml
yolo9/models/detect/yolov9-cf.yaml
yolo9/models/detect/yolov9-e.yaml
yolo9/models/detect/yolov9-m.yaml
yolo9/models/detect/yolov9-s.yaml
yolo9/models/detect/yolov9-t.yaml
yolo9/models/detect/yolov9.yaml
yolo9/models/hub/anchors.yaml
yolo9/models/hub/yolov3-spp.yaml
yolo9/models/hub/yolov3-tiny.yaml
yolo9/models/hub/yolov3.yaml
yolo9/models/panoptic/gelan-c-pan.yaml
yolo9/models/panoptic/yolov7-af-pan.yaml
yolo9/models/segment/gelan-c-dseg.yaml
yolo9/models/segment/gelan-c-seg.yaml
yolo9/models/segment/yolov7-af-seg.yaml
yolo9/models/segment/yolov9-c-dseg.yaml
yolo9/panoptic/predict.py
yolo9/panoptic/train.py
yolo9/panoptic/val.py
yolo9/segment/predict.py
yolo9/segment/train.py
yolo9/segment/train_dual.py
yolo9/segment/val.py
yolo9/segment/val_dual.py
yolo9/utils/__init__.py
yolo9/utils/activations.py
yolo9/utils/augmentations.py
yolo9/utils/autoanchor.py
yolo9/utils/autobatch.py
yolo9/utils/callbacks.py
yolo9/utils/coco_utils.py
yolo9/utils/dataloaders.py
yolo9/utils/downloads.py
yolo9/utils/general.py
yolo9/utils/lion.py
yolo9/utils/loss.py
yolo9/utils/loss_tal.py
yolo9/utils/loss_tal_dual.py
yolo9/utils/loss_tal_triple.py
yolo9/utils/metrics.py
yolo9/utils/plots.py
yolo9/utils/torch_utils.py
yolo9/utils/triton.py
yolo9-1.0.9.dist-info/licenses/LICENSE.md
yolo9-1.0.9.dist-info/METADATA
yolo9-1.0.9.dist-info/WHEEL
yolo9-1.0.9.dist-info/top_level.txt
yolo9-1.0.9.dist-info/RECORD
