Metadata-Version: 2.4
Name: yolo9
Version: 1.0.9
Summary: Package version of WongKinYiu/yolov9
Requires-Python: >=3.11
License-File: LICENSE.md
Requires-Dist: gitpython
Requires-Dist: ipython
Requires-Dist: matplotlib>=3.2.2
Requires-Dist: numpy>=1.18.5
Requires-Dist: opencv-python>=4.1.1
Requires-Dist: Pillow>=7.1.2
Requires-Dist: psutil
Requires-Dist: PyYAML>=5.3.1
Requires-Dist: requests>=2.23.0
Requires-Dist: scipy>=1.4.1
Requires-Dist: thop>=0.1.1
Requires-Dist: torch>=1.7.0
Requires-Dist: torchvision>=0.8.1
Requires-Dist: tqdm>=4.64.0
Requires-Dist: pandas>=1.1.4
Requires-Dist: seaborn>=0.11.0
Requires-Dist: albumentations>=1.0.3
Requires-Dist: pycocotools>=2.0
Dynamic: license-file
